{
	"40001": {
		"id": 40001,
		"hp": 3,
		"name": "植物lv1",
		"tip": "收益  20000   \\n成长80s  攻+1防+1血+3",
		"time": "20/20/20/20",
		"buy": 10000,
		"defense": 1,
		"harvest": 20000,
		"attack": 1,
		"moneyType": null
	},
	"40002": {
		"id": 40002,
		"hp": 3,
		"name": "植物lv2",
		"tip": "收益  50000   \\n成长100s 攻+1防+1血+3",
		"time": "25/25/25/25",
		"buy": 20000,
		"defense": 1,
		"harvest": 50000,
		"attack": 1,
		"moneyType": null
	},
	"40003": {
		"id": 40003,
		"hp": 3,
		"name": "植物lv3",
		"tip": "收益 100000   \\n成长120s 攻+1防+1血+3",
		"time": "30/30/30/30",
		"buy": 40000,
		"defense": 1,
		"harvest": 100000,
		"attack": 1,
		"moneyType": null
	},
	"40004": {
		"id": 40004,
		"hp": 30,
		"name": "植物lv4",
		"tip": "收益 1000000  \\n成长120s 攻10防10血30",
		"time": "30/30/30/30",
		"buy": 10,
		"defense": 10,
		"harvest": 1000000,
		"attack": 10,
		"moneyType": 1
	},
	"40005": {
		"id": 40005,
		"hp": 300,
		"name": "植物lv5",
		"tip": "收益 20000000 \\n成长120s 攻100防100血300",
		"time": "30/30/30/30",
		"buy": 200,
		"defense": 100,
		"harvest": 20000000,
		"attack": 100,
		"moneyType": 1
	},
	"61000": {
		"id": 61000,
		"hp": null,
		"name": "战舰零件",
		"tip": "600晶石购买1个战舰零件",
		"time": null,
		"buy": 600,
		"defense": null,
		"harvest": null,
		"attack": null,
		"moneyType": 1
	},
	"48001": {
		"id": 48001,
		"hp": null,
		"name": "扭蛋7",
		"tip": "随机获得2-5级\\n种子",
		"time": null,
		"buy": 500000,
		"defense": null,
		"harvest": null,
		"attack": null,
		"moneyType": null
	},
	"48002": {
		"id": 48002,
		"hp": null,
		"name": "扭蛋8",
		"tip": "随机获得3-5级\\n种子",
		"time": null,
		"buy": 20,
		"defense": null,
		"harvest": null,
		"attack": null,
		"moneyType": 1
	},
	"10001": {
		"id": 10001,
		"hp": null,
		"name": "神器lv1",
		"tip": "收益  20000   \\n成长80s    攻击+3",
		"time": "20/20/20/20",
		"buy": 10000,
		"defense": null,
		"harvest": 20000,
		"attack": 3,
		"moneyType": null
	},
	"10002": {
		"id": 10002,
		"hp": null,
		"name": "神器lv2",
		"tip": "收益  50000   \\n成长100s   攻击+3",
		"time": "25/25/25/25",
		"buy": 20000,
		"defense": null,
		"harvest": 50000,
		"attack": 3,
		"moneyType": null
	},
	"10003": {
		"id": 10003,
		"hp": null,
		"name": "神器lv3",
		"tip": "收益 100000   \\n成长120s   攻击+3",
		"time": "30/30/30/30",
		"buy": 40000,
		"defense": null,
		"harvest": 100000,
		"attack": 3,
		"moneyType": null
	},
	"10004": {
		"id": 10004,
		"hp": null,
		"name": "神器lv4",
		"tip": "收益 1000000  \\n成长120s   攻击+30",
		"time": "30/30/30/30",
		"buy": 10,
		"defense": null,
		"harvest": 1000000,
		"attack": 30,
		"moneyType": 1
	},
	"10005": {
		"id": 10005,
		"hp": null,
		"name": "神器lv5",
		"tip": "收益 20000000 \\n成长120s   攻击+300",
		"time": "30/30/30/30",
		"buy": 200,
		"defense": null,
		"harvest": 20000000,
		"attack": 300,
		"moneyType": 1
	},
	"18001": {
		"id": 18001,
		"hp": null,
		"name": "扭蛋1",
		"tip": "随机获得2-5级\\n种子",
		"time": null,
		"buy": 500000,
		"defense": null,
		"harvest": null,
		"attack": null,
		"moneyType": null
	},
	"18002": {
		"id": 18002,
		"hp": null,
		"name": "扭蛋2",
		"tip": "随机获得3-5级\\n种子",
		"time": null,
		"buy": 20,
		"defense": null,
		"harvest": null,
		"attack": null,
		"moneyType": 1
	},
	"80001": {
		"id": 80001,
		"hp": null,
		"name": "黄金领主",
		"tip": "通关攻占第一个星球获得的称号",
		"time": null,
		"buy": null,
		"defense": null,
		"harvest": null,
		"attack": null,
		"moneyType": null
	},
	"20001": {
		"id": 20001,
		"hp": null,
		"name": "机甲lv1",
		"tip": "收益  20000   \\n成长80s    防御+3",
		"time": "20/20/20/20",
		"buy": 10000,
		"defense": 3,
		"harvest": 20000,
		"attack": null,
		"moneyType": null
	},
	"20002": {
		"id": 20002,
		"hp": null,
		"name": "机甲lv2",
		"tip": "收益  50000   \\n成长100s   防御+3",
		"time": "25/25/25/25",
		"buy": 20000,
		"defense": 3,
		"harvest": 50000,
		"attack": null,
		"moneyType": null
	},
	"20003": {
		"id": 20003,
		"hp": null,
		"name": "机甲lv3",
		"tip": "收益 100000   \\n成长120s   防御+3",
		"time": "30/30/30/30",
		"buy": 40000,
		"defense": 3,
		"harvest": 100000,
		"attack": null,
		"moneyType": null
	},
	"20004": {
		"id": 20004,
		"hp": null,
		"name": "机甲lv4",
		"tip": "收益 1000000  \\n成长120s   防御+30",
		"time": "30/30/30/30",
		"buy": 10,
		"defense": 30,
		"harvest": 1000000,
		"attack": null,
		"moneyType": 1
	},
	"20005": {
		"id": 20005,
		"hp": null,
		"name": "机甲lv5",
		"tip": "收益 20000000 \\n成长120s   防御+300",
		"time": "30/30/30/30",
		"buy": 200,
		"defense": 300,
		"harvest": 20000000,
		"attack": null,
		"moneyType": 1
	},
	"28001": {
		"id": 28001,
		"hp": null,
		"name": "扭蛋3",
		"tip": "随机获得2-5级\\n种子",
		"time": null,
		"buy": 500000,
		"defense": null,
		"harvest": null,
		"attack": null,
		"moneyType": null
	},
	"28002": {
		"id": 28002,
		"hp": null,
		"name": "扭蛋4",
		"tip": "随机获得3-5级\\n种子",
		"time": null,
		"buy": 20,
		"defense": null,
		"harvest": null,
		"attack": null,
		"moneyType": 1
	},
	"61001": {
		"id": 61001,
		"hp": null,
		"name": "星际战舰",
		"tip": "可在每场战斗中使用一次，具有超高伤害",
		"time": null,
		"buy": null,
		"defense": null,
		"harvest": null,
		"attack": null,
		"moneyType": null
	},
	"30001": {
		"id": 30001,
		"hp": 9,
		"name": "神兽lv1",
		"tip": "收益  20000   \\n成长80s    血量+9",
		"time": "20/20/20/20",
		"buy": 10000,
		"defense": null,
		"harvest": 20000,
		"attack": null,
		"moneyType": null
	},
	"30002": {
		"id": 30002,
		"hp": 9,
		"name": "神兽lv2",
		"tip": "收益  50000   \\n成长100s   血量+9",
		"time": "25/25/25/25",
		"buy": 20000,
		"defense": null,
		"harvest": 50000,
		"attack": null,
		"moneyType": null
	},
	"30003": {
		"id": 30003,
		"hp": 9,
		"name": "神兽lv3",
		"tip": "收益 100000   \\n成长120s   血量+9",
		"time": "30/30/30/30",
		"buy": 40000,
		"defense": null,
		"harvest": 100000,
		"attack": null,
		"moneyType": null
	},
	"30004": {
		"id": 30004,
		"hp": 90,
		"name": "神兽lv4",
		"tip": "收益 1000000  \\n成长120s   血量+90",
		"time": "30/30/30/30",
		"buy": 10,
		"defense": null,
		"harvest": 1000000,
		"attack": null,
		"moneyType": 1
	},
	"30005": {
		"id": 30005,
		"hp": 900,
		"name": "神兽lv5",
		"tip": "收益 20000000 \\n成长120s   血量+900",
		"time": "30/30/30/30",
		"buy": 200,
		"defense": null,
		"harvest": 20000000,
		"attack": null,
		"moneyType": 1
	},
	"38001": {
		"id": 38001,
		"hp": null,
		"name": "扭蛋5",
		"tip": "随机获得2-5级\\n种子",
		"time": null,
		"buy": 500000,
		"defense": null,
		"harvest": null,
		"attack": null,
		"moneyType": null
	},
	"38002": {
		"id": 38002,
		"hp": null,
		"name": "扭蛋6",
		"tip": "随机获得3-5级\\n种子",
		"time": null,
		"buy": 20,
		"defense": null,
		"harvest": null,
		"attack": null,
		"moneyType": 1
	}
}